matecat_api/__init__.py
matecat_api/api_client.py
matecat_api/configuration.py
matecat_api/rest.py
matecat_api/api/__init__.py
matecat_api/api/engines_api.py
matecat_api/api/glossary_api.py
matecat_api/api/job_api.py
matecat_api/api/languages_api.py
matecat_api/api/options_api.py
matecat_api/api/project_api.py
matecat_api/api/quality_report_api.py
matecat_api/api/teams_api.py
matecat_api/api/tm_keys_api.py
matecat_api/api/translation_issues_api.py
matecat_api/api/translation_versions_api.py
matecat_api/models/__init__.py
matecat_api/models/body.py
matecat_api/models/body1.py
matecat_api/models/body10.py
matecat_api/models/body11.py
matecat_api/models/body12.py
matecat_api/models/body13.py
matecat_api/models/body14.py
matecat_api/models/body2.py
matecat_api/models/body3.py
matecat_api/models/body4.py
matecat_api/models/body5.py
matecat_api/models/body6.py
matecat_api/models/body7.py
matecat_api/models/body8.py
matecat_api/models/body9.py
matecat_api/models/change_password_response.py
matecat_api/models/change_status.py
matecat_api/models/chunk.py
matecat_api/models/comment.py
matecat_api/models/comments.py
matecat_api/models/completion_status_item.py
matecat_api/models/completion_status_item_project_status.py
matecat_api/models/completion_status_item_project_status_revise.py
matecat_api/models/data_status.py
matecat_api/models/engine.py
matecat_api/models/engines_list.py
matecat_api/models/error.py
matecat_api/models/error_errors.py
matecat_api/models/extended_job.py
matecat_api/models/extended_job_item.py
matecat_api/models/files.py
matecat_api/models/issue.py
matecat_api/models/job.py
matecat_api/models/job_file.py
matecat_api/models/job_translator_item.py
matecat_api/models/job_url.py
matecat_api/models/jobs.py
matecat_api/models/jobs_status.py
matecat_api/models/key.py
matecat_api/models/keys_list.py
matecat_api/models/language.py
matecat_api/models/languages.py
matecat_api/models/new_project.py
matecat_api/models/options.py
matecat_api-1.0.0.dist-info/METADATA
matecat_api-1.0.0.dist-info/WHEEL
matecat_api-1.0.0.dist-info/top_level.txt
matecat_api-1.0.0.dist-info/RECORD
